{
  "name": "Phantom Darkness (Box)",
  "code": "PTDN_B",
  "type": "Box",
  "date": "13-02-2008",
  "image": "https://crystal-cdn2.crystalcommerce.com/photos/352225/phantom_darkness_1st.jpg",
  "pull_type": "composition",
  "sub_sets": [
    "PTDN",
    "PTDN",
    "PTDN",
    "PTDN",
    "PTDN",
    "PTDN",
    "PTDN",
    "PTDN",
    "PTDN",
    "PTDN",
    "PTDN",
    "PTDN",
    "PTDN",
    "PTDN",
    "PTDN",
    "PTDN",
    "PTDN",
    "PTDN",
    "PTDN",
    "PTDN",
    "PTDN",
    "PTDN",
    "PTDN",
    "PTDN"
  ]
}
